logitboost/__init__.py
logitboost/logitboost.py
logitboost-0.7.dist-info/LICENSE
logitboost-0.7.dist-info/METADATA
logitboost-0.7.dist-info/WHEEL
logitboost-0.7.dist-info/top_level.txt
logitboost-0.7.dist-info/RECORD
